Metadata-Version: 2.1
Name: iqra
Version: 1.0.0
Summary: iqra, a library management program.
Home-page: https://github.com/alghafli/iqra
Author: Mohammad Alghafli
Author-email: thebsom@gmail.com
License: UNKNOWN
Keywords: library management program
Platform: UNKNOWN
Classifier: Development Status :: 4 - Beta
Classifier: License :: OSI Approved :: GNU General Public License v3 (GPLv3)
Classifier: Programming Language :: Python :: 3.5
Provides-Extra: cairo
